PyLoris/__init__.py
PyLoris/cleanUrl.py
PyLoris/slowloris.py
PyLoris-1.0.2.dist-info/LICENSE
PyLoris-1.0.2.dist-info/METADATA
PyLoris-1.0.2.dist-info/WHEEL
PyLoris-1.0.2.dist-info/top_level.txt
PyLoris-1.0.2.dist-info/RECORD
