Metadata-Version: 2.1
Name: PyLoris
Version: 1.0.2
Summary: Test websites for slow loris
Home-page: https://github.com/YoloFTW/PyLoris
Author: YoloFTW
License: UNKNOWN
Keywords: python,slow loris,test,loris,slow lorris
Platform: UNKNOWN
Classifier: Development Status :: 2 - Pre-Alpha
Classifier: Intended Audience :: Developers
Classifier: Programming Language :: Python :: 3
Classifier: Operating System :: Microsoft :: Windows
License-File: LICENSE
